{"index.md":"673b6f7b","pages_badge.md":"fe26e17d","pages_banner.md":"16987830","pages_browser-automation.md":"bef36b0c","pages_button.md":"f3c6ae7d","pages_clear.md":"1c2b1891","pages_confirm.md":"80a9b391","pages_contributing.md":"dea47a08","pages_dark-mode.md":"d6d314d2","pages_datetime.md":"81ddf743","pages_dropdown.md":"9b0e0f95","pages_empty.md":"e2bdfe51","pages_error.md":"3e87ac9d","pages_fonts.md":"5da60f09","pages_foundation.md":"21768bcb","pages_installation.md":"990140dd","pages_introduction.md":"fe579e6f","pages_label.md":"56ca018d","pages_menu.md":"faa61701","pages_metric.md":"cbdb0931","pages_modal.md":"a5f0b250","pages_notice.md":"8b254a86","pages_notification.md":"c9f26df0","pages_optional.md":"7c79dc9d","pages_password.md":"f865a899","pages_prompt.md":"45c2eeaf","pages_requirements.md":"3b6aea7c","pages_share.md":"ba9281d1","pages_sticker.md":"2b3f7e03","pages_switch.md":"bc18bc63","pages_tags.md":"95a054b7","pages_textbox.md":"745136fc","pages_writer.md":"9e7dbd30","playgrounds_badge_index.md":"5456ad5e","playgrounds_banner_index.md":"756a397b","playgrounds_button_index.md":"d17b69d7","playgrounds_datetime_index.md":"673395eb","playgrounds_dropdown_index.md":"2b163649","playgrounds_empty_index.md":"698e68d6","playgrounds_error_index.md":"af4e667f","playgrounds_label_index.md":"a27ad78d","playgrounds_notice_index.md":"dbd4d2bd","playgrounds_optional_index.md":"36b539d0","playgrounds_password_index.md":"53ecb8ad","playgrounds_switch_index.md":"1d8c9881","playgrounds_textbox_index.md":"bd36bd9a","playgrounds_writer_index.md":"7215dcc4"}
